quickie/__init__.py
quickie/__main__.py
quickie/_argparser.py
quickie/_cli.py
quickie/_init.py
quickie/_meta.py
quickie/_namespace.py
quickie/_version.py
quickie/config.py
quickie/context.py
quickie/errors.py
quickie/factories.py
quickie/tasks.py
quickie/completion/__init__.py
quickie/completion/_internal.py
quickie/completion/base.py
quickie/completion/python.py
quickie/conditions/__init__.py
quickie/conditions/base.py
quickie/utils/__init__.py
quickie/utils/argparser.py
quickie/utils/console.py
quickie/utils/imports.py
quickie_runner-0.5.1.dist-info/METADATA
quickie_runner-0.5.1.dist-info/WHEEL
quickie_runner-0.5.1.dist-info/entry_points.txt
quickie_runner-0.5.1.dist-info/licenses/LICENSE
quickie_runner-0.5.1.dist-info/RECORD
