Metadata-Version: 2.4
Name: quickie-runner
Version: 0.5.1
Summary: A CLI tool for quick tasks.
Project-URL: Homepage, https://github.com/adrianmrit/quickie
Project-URL: Documentation, https://quickie.readthedocs.io
Project-URL: Repository, https://github.com/adrianmrit/quickie.git
Project-URL: Issues, https://github.com/adrianmrit/quickie/issues
Project-URL: Changelog, https://github.com/adrianmrit/quickie/blob/main/CHANGELOG.md
Author-email: Adrian Martinez Rodriguez <adrianmrit@gmail.com>
License: The MIT License
License-File: LICENSE
Keywords: CLI,quick,tasks
Classifier: Development Status :: 3 - Alpha
Classifier: Environment :: Console
Classifier: Intended Audience :: Developers
Classifier: License :: OSI Approved :: MIT License
Classifier: Programming Language :: Python :: 3.12
Requires-Python: >=3.12
Requires-Dist: argcomplete~=3.6
Requires-Dist: build>=1.2.2.post1
Requires-Dist: frozendict~=2.4
Requires-Dist: oslex~=0.1
Requires-Dist: python-dotenv~=1.1
Requires-Dist: rich~=14.0
